GMMClusteringAlgorithms/__init__.py
GMMClusteringAlgorithms/classes/__init__.py
GMMClusteringAlgorithms/classes/_base.py
GMMClusteringAlgorithms/classes/_bayesian_gaussian_mixture.py
GMMClusteringAlgorithms/classes/_cluster_merger_gui.py
GMMClusteringAlgorithms/classes/_data_frame.py
GMMClusteringAlgorithms/classes/_gaussian_mixture_model.py
GMMClusteringAlgorithms/classes/_phase_first_gaussian_model.py
GMMClusteringAlgorithms/sklearn_mixture_piicr/__init__.py
GMMClusteringAlgorithms/sklearn_mixture_piicr/_base.py
GMMClusteringAlgorithms/sklearn_mixture_piicr/_bayesian_mixture.py
GMMClusteringAlgorithms/sklearn_mixture_piicr/_gaussian_mixture.py
GMMClusteringAlgorithms/sklearn_mixture_piicr/_phase_constrained_gaussian_mixture.py
GMMClusteringAlgorithms/sklearn_mixture_piicr/_strict_bayesian_mixture.py
GMMClusteringAlgorithms-0.1.28.dist-info/LICENSE.txt
GMMClusteringAlgorithms-0.1.28.dist-info/LICENSE_scikit_learn.txt
GMMClusteringAlgorithms-0.1.28.dist-info/METADATA
GMMClusteringAlgorithms-0.1.28.dist-info/WHEEL
GMMClusteringAlgorithms-0.1.28.dist-info/top_level.txt
GMMClusteringAlgorithms-0.1.28.dist-info/RECORD
