Metadata-Version: 2.1
Name: GMMClusteringAlgorithms
Version: 0.1.28
Summary: OBSOLETE. This package is no longer maintained because it has been replaced by the package piicrgmms.
Home-page: https://pypi.org/project/GMMClusteringAlgorithms/
Author: Colin Weber
Author-email: colin.weber.27@gmail.com
License: UNKNOWN
Project-URL: piicrgmms, https://pypi.org/project/piicrgmms/
Project-URL: Homepage, https://pypi.org/project/GMMClusteringAlgorithms/
Project-URL: Source code, https://github.com/colinweber27/GMMClusteringAlgorithms
Project-URL: Download, https://pypi.org/project/GMMClusteringAlgorithms/#files
Keywords: Gaussian Mixture Model,Clustering Algorithms,Machine Learning,Mass Spectroscopy
Platform: UNKNOWN
Classifier: Programming Language :: Python :: 3
Classifier: License :: OSI Approved :: MIT License
Classifier: Intended Audience :: Science/Research
Classifier: Natural Language :: English
Classifier: Operating System :: Microsoft :: Windows
Classifier: Topic :: Scientific/Engineering
Classifier: Topic :: Scientific/Engineering :: Artificial Intelligence
Classifier: Topic :: Scientific/Engineering :: Physics
Requires-Python: >=3.6
Requires-Dist: scikit-learn
Requires-Dist: pandas
Requires-Dist: matplotlib
Requires-Dist: lmfit
Requires-Dist: joblib
Requires-Dist: tqdm
Requires-Dist: pillow
Requires-Dist: webcolors
